LICENSE
README.md
setup.py
thsdata/__init__.py
thsdata/thsdata.py
thsdata.egg-info/PKG-INFO
thsdata.egg-info/SOURCES.txt
thsdata.egg-info/dependency_links.txt
thsdata.egg-info/requires.txt
thsdata.egg-info/top_level.txt