Metadata-Version: 2.4
Name: thsdata
Version: 0.1.0
Summary: 金融行情数据查询API
Author: 
Author-email: 
Keywords: python,thsdata
Classifier: Development Status :: 1 - Planning
Classifier: Intended Audience :: Developers
Classifier: Programming Language :: Python :: 3
Classifier: Operating System :: Unix
Classifier: Operating System :: MacOS :: MacOS X
Classifier: Operating System :: Microsoft :: Windows
License-File: LICENSE
Requires-Dist: requests>=2.22.2
Requires-Dist: pandas>=0.22.0
Requires-Dist: thsdk>=0.0.2
Requires-Dist: pytz>=2025.1
Dynamic: classifier
Dynamic: description
Dynamic: description-content-type
Dynamic: keywords
Dynamic: license-file
Dynamic: requires-dist
Dynamic: summary
